__init__.py
flamingo/__init__.py
flamingo/cli.py
flamingo/main.py
flamingo/algorithms/__init__.py
flamingo/algorithms/correction_methods.py
flamingo/algorithms/error_fit_functions.py
flamingo/core/__init__.py
flamingo/core/optimization_parameter.py
flamingo/core/processing_pipeline.py
flamingo/gui/__init__.py
flamingo/gui/app.py
flamingo/gui/components.py
flamingo/utils/__init__.py
flamingo/utils/config.py
flamingo/utils/helper_functions.py
flamingo/utils/log_capture.py
flamingo/utils/progress.py
flamingo/visualization/__init__.py
flamingo/visualization/plot_data.py
flamingo_thz-0.1.1.dist-info/licenses/LICENSE
flamingo_thz-0.1.1.dist-info/METADATA
flamingo_thz-0.1.1.dist-info/WHEEL
flamingo_thz-0.1.1.dist-info/entry_points.txt
flamingo_thz-0.1.1.dist-info/top_level.txt
flamingo_thz-0.1.1.dist-info/RECORD
