Metadata-Version: 2.4
Name: flamingo-thz
Version: 0.1.1
Summary: Data Correction Tool for THz Time Domain Spectroscopy
Author-email: Tim Vogel <32876663+TimVog@users.noreply.github.com>
License-Expression: MIT
Project-URL: Homepage, https://github.com/TimVog/flamingo
Project-URL: Repository, https://github.com/TimVog/flamingo
Classifier: Programming Language :: Python
Classifier: Programming Language :: Python :: 3.9
Classifier: Programming Language :: Python :: 3.10
Classifier: Programming Language :: Python :: 3.11
Classifier: Programming Language :: Python :: 3.12
Classifier: Operating System :: OS Independent
Requires-Python: >=3.9
License-File: LICENSE
Requires-Dist: numpy
Requires-Dist: scipy
Requires-Dist: matplotlib
Requires-Dist: h5py
Requires-Dist: tqdm
Requires-Dist: colorama
Requires-Dist: customtkinter>=5.1.2
Dynamic: license-file
